realML/__init__.py
realML/kernel/RFMPreconditionedGaussianKRRSolver.py
realML/kernel/RFMPreconditionedPolynomialKRRSolver.py
realML/kernel/TensorMachinesBinaryClassification.py
realML/kernel/TensorMachinesRegularizedLeastSquares.py
realML/kernel/__init__.py
realML/kernel/preconditionedKRR.py
realML/kernel/sfo.py
realML/kernel/tensormachines.py
realML/matrix/FastLADSolver.py
realML/matrix/L1LowRank.py
realML/matrix/LADregression.py
realML/matrix/__init__.py
realML/matrix/approxL1LowRankDecomposition.py
realML/matrix/randomizedpolypca.py
realML/matrix/robustsparsepca.py
realML/matrix/sdr.py
realML/matrix/sparsepca.py
realML/pipelines/FastLAD_pipeline.py
realML/pipelines/L1LowRank_pipeline.py
realML/pipelines/RFMPreconditionedGaussianKRR_pipeline.py
realML/pipelines/RFMPreconditionedGaussianKRR_pipeline_196_autoMpg.py
realML/pipelines/RFMPreconditionedGaussianKRR_pipeline_26_radon_seed.py
realML/pipelines/RFMPreconditionedPolynomialKRR_pipeline.py
realML/pipelines/TensorMachinesBinaryClassification_pipeline.py
realML/pipelines/TensorMachinesRegularizedLeastSquares_pipeline.py
realML/pipelines/__init__.py
realML/pipelines/base.py
realML/pipelines/randomizedpolypca_pipeline.py
realML/pipelines/randomizedpolypca_pipeline_2.py
realML/pipelines/randomizedpolypca_pipeline_3.py
realML/pipelines/robustsparsepca_pipeline.py
realML/pipelines/robustsparsepca_pipeline_2.py
realML/pipelines/sparsepca_pipeline.py
realML/pipelines/sparsepca_pipeline_2.py
realML/pipelines/sparsepca_pipeline_3.py
realML/pipelines/sparsepca_pipeline_4.py
realML/pipelines/sparsepca_pipeline_5.py
realML/pipelines/sparsepca_pipeline_6.py
realML/pipelines/sparsepca_pipeline_old.py
realML-3.0.3.dist-info/LICENSE
realML-3.0.3.dist-info/METADATA
realML-3.0.3.dist-info/WHEEL
realML-3.0.3.dist-info/entry_points.txt
realML-3.0.3.dist-info/top_level.txt
realML-3.0.3.dist-info/RECORD
