Metadata-Version: 2.1
Name: realML
Version: 3.0.3
Summary: ICSI provided machine learning primitives for DARPA D3M project, focusing on fast kernel methods and matrix factorizations 
Home-page: https://gitlab.com/datadrivendiscovery/contrib/realML
Author: International Computer Science Institute
Author-email: gittea@rpi.edu
License: Apache License 2.0
Keywords: d3m_primitive,machine learning,regression,dimensionality reduction,low rank factorization,featurization,sufficient dimensionality reduction,kernel methods
Platform: UNKNOWN
Requires-Dist: numpy (>=1.14.0)
Requires-Dist: regex (>=2017.4.5)
Requires-Dist: scikit-learn (>=0.18.1)
Requires-Dist: scipy (>=1.2.1)
